scripts/__init__.py
scripts/run_pipeline.py
tests/__init__.py
vitoxreduce/__init__.py
vitoxreduce/bartpho_span_baseline.py
vitoxreduce/eval_metrics.py
vitoxreduce/pipeline.py
vitoxreduce/span_locator_inference.py
vitoxreduce/tier1_toxicity_detector.py
vitoxreduce/tier2_span_locator.py
vitoxreduce/tier3_rewrite_generator.py
vitoxreduce-1.0.3.dist-info/METADATA
vitoxreduce-1.0.3.dist-info/WHEEL
vitoxreduce-1.0.3.dist-info/entry_points.txt
vitoxreduce-1.0.3.dist-info/top_level.txt
vitoxreduce-1.0.3.dist-info/RECORD
