Metadata-Version: 2.4
Name: vitoxreduce
Version: 1.0.3
Summary: A comprehensive pipeline for reducing toxicity in text
Home-page: https://github.com/danny2904/vitoxreduce
Author: joshswift294
Author-email: joshswift294@gmail.com
License: Apache-2.0
Classifier: Development Status :: 4 - Beta
Classifier: Intended Audience :: Developers
Classifier: Intended Audience :: Science/Research
Classifier: Topic :: Scientific/Engineering :: Artificial Intelligence
Classifier: Topic :: Text Processing :: Linguistic
Classifier: License :: OSI Approved :: Apache Software License
Classifier: Programming Language :: Python :: 3
Classifier: Programming Language :: Python :: 3.7
Classifier: Programming Language :: Python :: 3.8
Classifier: Programming Language :: Python :: 3.9
Classifier: Programming Language :: Python :: 3.10
Requires-Python: >=3.7
Requires-Dist: torch>=1.9.0
Requires-Dist: transformers>=4.21.0
Requires-Dist: numpy>=1.21.0
Requires-Dist: tqdm>=4.62.0
Requires-Dist: scikit-learn>=1.0.0
Requires-Dist: sentence-transformers>=2.2.0
Requires-Dist: nltk>=3.6.0
Requires-Dist: pyvi>=0.1.0
Dynamic: author
Dynamic: author-email
Dynamic: classifier
Dynamic: description
Dynamic: description-content-type
Dynamic: home-page
Dynamic: license
Dynamic: requires-dist
Dynamic: requires-python
Dynamic: summary
